{
  "index": {
    "title": "Introduction",
    "theme": {
      "breadcrumb": false,
      "toc": false
    }
  },
  "flow": {
    "title": "Flow of funds",
    "theme": {
      "breadcrumb": false,
      "toc": true
    }
  },
  "developers": {
    "type": "separator",
    "title": "Dev tools"
  },
  "sdk": {
    "title": "SDK",
    "theme": {
      "collapsed": true
    }
  },
  "sdk-ethers": {
    "display": "hidden"
  },
  "react": "React SDK",
  "react-ethers": {
    "display": "hidden"
  },
  "splits-kit": "SplitsKit",
  "subgraph": "Subgraph",
  "protocol": {
    "type": "separator",
    "title": "Contracts"
  },
  "core": "Core contracts",
  "templates": "Templates",
  "app_support": {
    "type": "page",
    "title": "App Support",
    "href": "https://splits.org/help/",
    "newWindow": true
  },
  "about": {
    "type": "page",
    "title": "Home",
    "href": "https://splits.org/",
    "newWindow": true
  }
}
